polars_interval_match-0.1.31.dist-info/METADATA
polars_interval_match-0.1.31.dist-info/WHEEL
polars_interval_match/__init__.py
polars_interval_match/_interval_match.cpython-311-darwin.so
polars_interval_match-0.1.31.dist-info/RECORD
